LICENSE
README.md
pyproject.toml
osrs_hiscores/client.py
osrs_hiscores/enums.py
osrs_hiscores/models.py
osrs_hiscores_client.egg-info/PKG-INFO
osrs_hiscores_client.egg-info/SOURCES.txt
osrs_hiscores_client.egg-info/dependency_links.txt
osrs_hiscores_client.egg-info/requires.txt
osrs_hiscores_client.egg-info/top_level.txt
tests/test_all.py