Metadata-Version: 2.4
Name: osrs-hiscores-client
Version: 3.0.0
Summary: Python client for Old School RuneScape Hiscores API.
Author: Valtteri Remes
License-Expression: MIT
Project-URL: Homepage, https://github.com/vremes/osrs-hiscores
Project-URL: Documentation, https://github.com/vremes/osrs-hiscores
Project-URL: Repository, https://github.com/vremes/osrs-hiscores.git
Project-URL: Issues, https://github.com/vremes/osrs-hiscores/issues
Keywords: osrs,hiscores,runescape,api,client
Classifier: Programming Language :: Python :: 3
Classifier: Operating System :: OS Independent
Requires-Python: >=3.10
License-File: LICENSE
Requires-Dist: requests>=2.31.0
Dynamic: license-file
